django_dramatiq_charts/__init__.py
django_dramatiq_charts/config.py
django_dramatiq_charts/consts.py
django_dramatiq_charts/forms.py
django_dramatiq_charts/views.py
django_dramatiq_charts/static/django_dramatiq_charts/base.css
django_dramatiq_charts/static/django_dramatiq_charts/favicon.png
django_dramatiq_charts/static/django_dramatiq_charts/libs/jquery/jquery-3.6.0.min.js
django_dramatiq_charts/static/django_dramatiq_charts/libs/plotly/plotly-2.8.3.min.js
django_dramatiq_charts/static/django_dramatiq_charts/libs/select2/select2.min.css
django_dramatiq_charts/static/django_dramatiq_charts/libs/select2/select2.min.js
django_dramatiq_charts/templates/django_dramatiq_charts/base.html
django_dramatiq_charts/templates/django_dramatiq_charts/load_chart.html
django_dramatiq_charts/templates/django_dramatiq_charts/timeline_chart.html
django_dramatiq_charts-0.4.0.dist-info/licenses/LICENSE
django_dramatiq_charts-0.4.0.dist-info/METADATA
django_dramatiq_charts-0.4.0.dist-info/WHEEL
django_dramatiq_charts-0.4.0.dist-info/top_level.txt
django_dramatiq_charts-0.4.0.dist-info/RECORD
