Metadata-Version: 2.4
Name: django-dramatiq-charts
Version: 0.4.0
Summary: Charts for django_dramatic
Home-page: https://github.com/ikvk/django_dramatiq_charts
Author: Vladimir Kaukin
Author-email: KaukinVK@ya.ru
License: Apache-2.0
Keywords: django_dramatiq,chart,diagram,graph,dashboard,python3,python
Classifier: Programming Language :: Python :: 3
Classifier: License :: OSI Approved :: Apache Software License
Classifier: Operating System :: OS Independent
License-File: LICENSE
Dynamic: author
Dynamic: author-email
Dynamic: classifier
Dynamic: description
Dynamic: description-content-type
Dynamic: home-page
Dynamic: keywords
Dynamic: license
Dynamic: license-file
Dynamic: summary
